pyvisim/__init__.py
pyvisim/_base_classes.py
pyvisim/_config.py
pyvisim/_errors.py
pyvisim/_utils.py
pyvisim/eval.py
pyvisim/datasets/__init__.py
pyvisim/datasets/datasets.py
pyvisim/encoders/__init__.py
pyvisim/encoders/_base_encoder.py
pyvisim/encoders/fisher_vector.py
pyvisim/encoders/pipeline.py
pyvisim/encoders/vlad.py
pyvisim/features/__init__.py
pyvisim/features/_features.py
pyvisim/losses/__init__.py
pyvisim/losses/_losses.py
pyvisim/res/logging_config.yaml
pyvisim/res/model_files/gmm_k256_deep_features_vgg16_no_pca.pkl
pyvisim/res/model_files/gmm_k256_deep_features_vgg16_pca.pkl
pyvisim/res/model_files/gmm_k256_root_sift_no_pca.pkl
pyvisim/res/model_files/gmm_k256_root_sift_pca.pkl
pyvisim/res/model_files/gmm_k256_sift_no_pca.pkl
pyvisim/res/model_files/gmm_k256_sift_pca.pkl
pyvisim/res/model_files/k_means_k256_deep_features_vgg16_no_pca.pkl
pyvisim/res/model_files/k_means_k256_deep_features_vgg16_pca.pkl
pyvisim/res/model_files/k_means_k256_root_sift_no_pca.pkl
pyvisim/res/model_files/k_means_k256_root_sift_pca.pkl
pyvisim/res/model_files/k_means_k256_sift_no_pca.pkl
pyvisim/res/model_files/k_means_k256_sift_pca.pkl
pyvisim/res/model_files/pca_k256_deep_features_vgg16_f2.pkl
pyvisim/res/model_files/pca_k256_root_sift_f2.pkl
pyvisim/res/model_files/pca_k256_sift_f2.pkl
pyvisim-0.1.3.dist-info/LICENSE
pyvisim-0.1.3.dist-info/METADATA
pyvisim-0.1.3.dist-info/WHEEL
pyvisim-0.1.3.dist-info/top_level.txt
pyvisim-0.1.3.dist-info/RECORD
